cpyfunctional/__init__.py
cpyfunctional/core.py
cpyfunctional/cpyfunctional.py
Cpyfunctional-0.0.2.dist-info/LICENSE
Cpyfunctional-0.0.2.dist-info/METADATA
Cpyfunctional-0.0.2.dist-info/WHEEL
Cpyfunctional-0.0.2.dist-info/top_level.txt
Cpyfunctional-0.0.2.dist-info/RECORD
