Metadata-Version: 2.1
Name: Cpyfunctional
Version: 0.0.2
Summary: A python package to help you code python in functional programming paradigm.
Home-page: https://github.com/3mp3ri0r/cpyfunctional/
Author: Christoforus Surjoputro
Author-email: cs_sanmar@yahoo.com
License: MIT
Platform: any
Classifier: Development Status :: 3 - Alpha
Classifier: Environment :: Plugins
Classifier: Intended Audience :: Developers
Classifier: License :: OSI Approved :: MIT License
Classifier: Operating System :: OS Independent
Classifier: Programming Language :: Python
Classifier: Programming Language :: Python :: 3.4
Classifier: Programming Language :: Python :: 3.5
Classifier: Programming Language :: Python :: 3.6
Classifier: Programming Language :: Python :: 3.7
Classifier: Topic :: Software Development :: Libraries
Classifier: Topic :: Software Development :: Libraries :: Python Modules
Classifier: Topic :: Utilities
Requires-Python: ~=3.4
Requires-Dist: typing ; python_version < "3.5"
Provides-Extra: dev
Requires-Dist: coverage ; extra == 'dev'
Requires-Dist: mypy ; extra == 'dev'
